server/__init__.py
server/descs.py
server/metaclasses.py
server/server.py
server/server_database.py
server/common/__init__.py
server/common/decorators.py
server/common/errors.py
server/common/utils.py
server/common/variables.py
server/log/__init__.py
server/log/client_log_config.py
server/log/server_log_config.py
server/ui/__init__.py
server/ui/gui.py
server/ui/registration.py
server/ui/server_gui.py
server/ui/settings_gui.py
server/ui/statistics_gui.py
server/unit_tests/__init__.py
server/unit_tests/test_client.py
server/unit_tests/test_server.py
server/unit_tests/test_utils.py
gui_messenger_server-0.0.1.dist-info/METADATA
gui_messenger_server-0.0.1.dist-info/WHEEL
gui_messenger_server-0.0.1.dist-info/top_level.txt
gui_messenger_server-0.0.1.dist-info/RECORD
